prometheus_mcp_server/__init__.py
prometheus_mcp_server/logging_config.py
prometheus_mcp_server/main.py
prometheus_mcp_server/server.py
raihan0824_prometheus_mcp_server-1.2.13.dist-info/licenses/LICENSE
raihan0824_prometheus_mcp_server-1.2.13.dist-info/METADATA
raihan0824_prometheus_mcp_server-1.2.13.dist-info/WHEEL
raihan0824_prometheus_mcp_server-1.2.13.dist-info/entry_points.txt
raihan0824_prometheus_mcp_server-1.2.13.dist-info/top_level.txt
raihan0824_prometheus_mcp_server-1.2.13.dist-info/RECORD
