Metadata-Version: 2.4
Name: raihan0824-prometheus-mcp-server
Version: 1.2.13
Summary: MCP server for Prometheus integration
Author-email: raihan0824 <mraihanafiandi@gmail.com>
Maintainer-email: raihan0824 <mraihanafiandi@gmail.com>
License-Expression: MIT
Project-URL: Homepage, https://github.com/raihan0824/prometheus-mcp-server
Project-URL: Repository, https://github.com/raihan0824/prometheus-mcp-server
Project-URL: Issues, https://github.com/raihan0824/prometheus-mcp-server/issues
Project-URL: Documentation, https://github.com/raihan0824/prometheus-mcp-server/blob/main/README.md
Keywords: prometheus,mcp,monitoring,metrics,claude,ai
Classifier: Development Status :: 4 - Beta
Classifier: Intended Audience :: Developers
Classifier: Programming Language :: Python :: 3
Classifier: Programming Language :: Python :: 3.10
Classifier: Programming Language :: Python :: 3.11
Classifier: Programming Language :: Python :: 3.12
Classifier: Topic :: System :: Monitoring
Classifier: Topic :: Software Development :: Libraries :: Python Modules
Requires-Python: >=3.10
License-File: LICENSE
Requires-Dist: mcp>=1.2.0
Requires-Dist: prometheus-api-client
Requires-Dist: python-dotenv
Requires-Dist: pyproject-toml>=0.1.0
Requires-Dist: requests
Requires-Dist: structlog>=23.0.0
Requires-Dist: pydantic<3.0.0,>=2.11.0
Requires-Dist: httpx>=0.27.1
Provides-Extra: dev
Requires-Dist: pytest>=7.0.0; extra == "dev"
Requires-Dist: pytest-cov>=4.0.0; extra == "dev"
Requires-Dist: pytest-asyncio>=0.21.0; extra == "dev"
Requires-Dist: pytest-mock>=3.10.0; extra == "dev"
Requires-Dist: docker>=7.0.0; extra == "dev"
Requires-Dist: requests>=2.31.0; extra == "dev"
Dynamic: license-file
